torchdensityratio/__init__.py
torchdensityratio/rulsif.py
torchdensityratio-1.0.1.dist-info/licenses/LICENSE
torchdensityratio-1.0.1.dist-info/METADATA
torchdensityratio-1.0.1.dist-info/WHEEL
torchdensityratio-1.0.1.dist-info/top_level.txt
torchdensityratio-1.0.1.dist-info/RECORD
