Metadata-Version: 2.4
Name: torchdensityratio
Version: 1.0.1
Summary: Density Ratio Estimation with PyTorch
Author-email: Filippo Airaldi <filippoairaldi@gmail.com>
License-Expression: MIT
Project-URL: Homepage, https://github.com/FilippoAiraldi/torch-density-ratio
Project-URL: Bug Tracker, https://github.com/FilippoAiraldi/torch-density-ratio/issues
Keywords: density-ratio-estimation,machine-learning,pytorch
Classifier: Programming Language :: Python
Classifier: Programming Language :: Python :: 3 :: Only
Classifier: Programming Language :: Python :: 3.10
Classifier: Programming Language :: Python :: 3.11
Classifier: Programming Language :: Python :: 3.12
Classifier: Programming Language :: Python :: 3.13
Classifier: Operating System :: OS Independent
Classifier: Intended Audience :: Science/Research
Classifier: Topic :: Scientific/Engineering :: Mathematics
Classifier: Topic :: Scientific/Engineering :: Artificial Intelligence
Requires-Python: >=3.10
License-File: LICENSE
Requires-Dist: torch>=2.7.0
Dynamic: license-file
